setup.cfg
setup.py
slamon_afm/__init__.py
slamon_afm/app.py
slamon_afm/cli.py
slamon_afm/models.py
slamon_afm.egg-info/PKG-INFO
slamon_afm.egg-info/SOURCES.txt
slamon_afm.egg-info/dependency_links.txt
slamon_afm.egg-info/entry_points.txt
slamon_afm.egg-info/requires.txt
slamon_afm.egg-info/top_level.txt
slamon_afm/routes/__init__.py
slamon_afm/routes/agent_routes.py
slamon_afm/routes/bpms_routes.py
slamon_afm/routes/dashboard.html
slamon_afm/routes/dashboard_routes.py
slamon_afm/routes/status_routes.py
slamon_afm/tests/__init__.py
slamon_afm/tests/afm_test.py
slamon_afm/tests/agent_routes_tests.py
slamon_afm/tests/bpms_routes_tests.py
slamon_afm/tests/dashboard_routes_tests.py
slamon_afm/tests/status_routes_tests.py