Metadata-Version: 1.1
Name: slamon-afm
Version: 1.1.0
Summary: SLAMon Agent Fleet Manager is part of the Coordinator, which controls deployed agents by giving them tasks and receiving the results. The results are then propagated to e.g. a business process management system (BPMS).
Home-page: https://github.com/SLAMon/slamon-agent-fleet-manager
Author: SLAMon
Author-email: slamon.organization@gmail.com
License: Apache License v2.0
Platform: Python 3.3+
Classifier: Operating System :: OS Independent
Classifier: Programming Language :: Python :: 3
Classifier: Programming Language :: Python :: 3.3
Classifier: Programming Language :: Python :: 3.4
Classifier: License :: OSI Approved :: Apache Software License
Classifier: Topic :: Software Development :: Libraries :: Python Modules
Classifier: Topic :: Software Development :: Quality Assurance
Classifier: Topic :: Software Development :: Testing
Classifier: Topic :: System :: Monitoring
